mcp_database_manager/__init__.py
mcp_database_manager/config.py
mcp_database_manager/db_manager.py
mcp_database_manager/server.py
mcp_database_manager-0.1.4.dist-info/METADATA
mcp_database_manager-0.1.4.dist-info/WHEEL
mcp_database_manager-0.1.4.dist-info/entry_points.txt
mcp_database_manager-0.1.4.dist-info/RECORD
