Metadata-Version: 2.4
Name: mcp-database-manager
Version: 0.1.4
Summary: MCP server for database management
Requires-Python: >=3.10
Requires-Dist: mcp
Requires-Dist: platformdirs
Requires-Dist: pydantic
Requires-Dist: pyyaml
Requires-Dist: sqlalchemy
Provides-Extra: all
Requires-Dist: cryptography; extra == 'all'
Requires-Dist: psycopg2-binary; extra == 'all'
Requires-Dist: pymssql; extra == 'all'
Requires-Dist: pymysql; extra == 'all'
Provides-Extra: mssql
Requires-Dist: pymssql; extra == 'mssql'
Provides-Extra: mysql
Requires-Dist: cryptography; extra == 'mysql'
Requires-Dist: pymysql; extra == 'mysql'
Provides-Extra: postgres
Requires-Dist: psycopg2-binary; extra == 'postgres'
